casino_bdata4_e/__init__.py
casino_bdata4_e/bingo.py
casino_bdata4_e/cards.py
casino_bdata4_e/dice.py
casino_bdata4_e/main.py
casino_bdata4_e/roulette.py
casino_bdata4_e-0.0.6.dist-info/LICENSE
casino_bdata4_e-0.0.6.dist-info/METADATA
casino_bdata4_e-0.0.6.dist-info/WHEEL
casino_bdata4_e-0.0.6.dist-info/top_level.txt
casino_bdata4_e-0.0.6.dist-info/RECORD
