Metadata-Version: 2.1
Name: casino_bdata4_e
Version: 0.0.6
Summary: Casino games library created by a group of 4 university students.
Author-email: joonroo <jon.rodrigueza@alumni.mondragon.edu>, ikerbenitod <iker.benitod@alumni.mondragon.edu>, "asier.lorenzo" <asier.lorenzoa@alumni.mondragon.edu>, "unai.penafiel" <unai.penafiel@alumni.mondragon.edu>
Project-URL: Homepage, https://github.com/uunaii/Trabajo_Progra.git
Classifier: Programming Language :: Python :: 3
Classifier: License :: OSI Approved :: MIT License
Classifier: Operating System :: OS Independent
Requires-Python: >=3.8
License-File: LICENSE
